flexiconc/__init__.py
flexiconc/concordance.py
flexiconc/corpus_old.py
flexiconc/flexiconc_config_default.ini
flexiconc/resources.py
flexiconc/test.py
flexiconc/text_import.py
flexiconc/trash.py
flexiconc/algorithms/__init__.py
flexiconc/algorithms/annotate_association_scores.py
flexiconc/algorithms/annotate_concordance_frequency_list.py
flexiconc/algorithms/annotate_sentence_transformers.py
flexiconc/algorithms/annotate_spacy_embeddings.py
flexiconc/algorithms/annotate_spacy_pos.py
flexiconc/algorithms/annotate_tf_idf.py
flexiconc/algorithms/cluster_context_tree.py
flexiconc/algorithms/clustering_hierarchical_embeddings.py
flexiconc/algorithms/clustering_random.py
flexiconc/algorithms/partition_by_embeddings.py
flexiconc/algorithms/partition_by_metadata_attribute.py
flexiconc/algorithms/partition_ngrams.py
flexiconc/algorithms/rank_by_collocations.py
flexiconc/algorithms/rank_kwic_grouper.py
flexiconc/algorithms/rank_number_of_rare_words.py
flexiconc/algorithms/select_by_metadata_attribute.py
flexiconc/algorithms/select_by_token_numeric_value.py
flexiconc/algorithms/select_by_token_string.py
flexiconc/algorithms/select_manual.py
flexiconc/algorithms/select_random.py
flexiconc/algorithms/select_rank_wrapper.py
flexiconc/algorithms/select_slot.py
flexiconc/algorithms/select_weighted_sample_by_metadata.py
flexiconc/algorithms/sort_by_corpus_position.py
flexiconc/algorithms/sort_by_token_attribute.py
flexiconc/algorithms/sort_random.py
flexiconc/trash/__init__.py
flexiconc/trash/partition_openai_semantic.py
flexiconc/trash/select_set_operation.py
flexiconc/trash/select_sort_wrapper.py
flexiconc/utils/__init__.py
flexiconc/utils/conditions.py
flexiconc/utils/cqp_parser_old.py
flexiconc/utils/cqp_tools.py
flexiconc/utils/helper_algorithms.py
flexiconc/utils/line_operations.py
flexiconc/utils/logging.py
flexiconc/utils/notebook_utils.py
flexiconc/utils/retrieve.py
flexiconc/utils/retrieve_resources.py
flexiconc/utils/sample_corpus.py
flexiconc/utils/wmatrix.py
flexiconc-0.1.20.dist-info/METADATA
flexiconc-0.1.20.dist-info/WHEEL
flexiconc-0.1.20.dist-info/top_level.txt
flexiconc-0.1.20.dist-info/RECORD
