Metadata-Version: 2.4
Name: FlexiConc
Version: 0.1.20
Summary: A Python package to assist concordance reading
Home-page: https://github.com/fau-klue/flexiconc
Author: RC21 (Nathan Dykes, Stephanie Evert, Michaela Mahlberg, Alexander Piperski @ Friedrich-Alexander-Universität Erlangen-Nürnberg)
Author-email: aleksandr.piperski@fau.de
Project-URL: Documentation, https://fau-klue.github.io/flexiconc-docs/
Classifier: Programming Language :: Python :: 3
Classifier: License :: OSI Approved :: MIT License
Classifier: Operating System :: OS Independent
Requires-Python: >=3.6
Requires-Dist: anytree>=2.12.1
Requires-Dist: networkx>=3.1
Requires-Dist: numpy<3.0,>=2.0
Requires-Dist: pandas<3.0,>=2.2.2
Requires-Dist: platformdirs>=4.3
Requires-Dist: jsonschema>=4.23.0
Requires-Dist: intervaltree>=3.0
Provides-Extra: partitioning
Requires-Dist: scikit_learn>=1.3.0; extra == "partitioning"
Provides-Extra: cwb
Requires-Dist: cwb-ccc>=0.12.4; extra == "cwb"
Provides-Extra: commercial
Requires-Dist: openai>=1.40.0; extra == "commercial"
Requires-Dist: pydantic>=1.8.2; extra == "commercial"
Provides-Extra: web
Requires-Dist: requests>=2.20.0; extra == "web"
Provides-Extra: icu
Requires-Dist: PyICU>=2.11; extra == "icu"
Provides-Extra: sorting
Requires-Dist: PyICU>=2.11; extra == "sorting"
Provides-Extra: annotation
Requires-Dist: spacy>=3.8.4; extra == "annotation"
Requires-Dist: sentence_transformers>=2.1.0; extra == "annotation"
Provides-Extra: notebooks
Requires-Dist: ipywidgets>=7.6.5; extra == "notebooks"
Provides-Extra: frequencies
Requires-Dist: wordfreq>=2.8.0; extra == "frequencies"
Provides-Extra: all
Requires-Dist: PyICU>=2.11; extra == "all"
Requires-Dist: cwb-ccc>=0.12.4; extra == "all"
Requires-Dist: ipywidgets>=7.6.5; extra == "all"
Requires-Dist: openai>=1.40.0; extra == "all"
Requires-Dist: pydantic>=1.8.2; extra == "all"
Requires-Dist: requests>=2.20.0; extra == "all"
Requires-Dist: scikit_learn>=1.3.0; extra == "all"
Requires-Dist: sentence_transformers>=2.1.0; extra == "all"
Requires-Dist: spacy>=3.8.4; extra == "all"
Requires-Dist: wordfreq>=2.8.0; extra == "all"
Dynamic: author
Dynamic: author-email
Dynamic: classifier
Dynamic: description
Dynamic: description-content-type
Dynamic: home-page
Dynamic: project-url
Dynamic: provides-extra
Dynamic: requires-dist
Dynamic: requires-python
Dynamic: summary
